leaf_focus/__init__.py
leaf_focus/app.py
leaf_focus/cli.py
leaf_focus/utils.py
leaf_focus/ocr/__init__.py
leaf_focus/ocr/keras_ocr.py
leaf_focus/ocr/model.py
leaf_focus/pdf/__init__.py
leaf_focus/pdf/model.py
leaf_focus/pdf/xpdf.py
leaf_focus-0.6.2.dist-info/LICENSE
leaf_focus-0.6.2.dist-info/METADATA
leaf_focus-0.6.2.dist-info/WHEEL
leaf_focus-0.6.2.dist-info/entry_points.txt
leaf_focus-0.6.2.dist-info/top_level.txt
leaf_focus-0.6.2.dist-info/RECORD
