Metadata-Version: 2.1
Name: leaf-focus
Version: 0.6.2
Summary: Extract structured text from pdf files.
Project-URL: Homepage, https://github.com/anotherbyte-net/leaf-focus
Project-URL: Changelog, https://github.com/anotherbyte-net/leaf-focus/blob/main/CHANGELOG.md
Project-URL: Source, https://github.com/anotherbyte-net/leaf-focus
Project-URL: Tracker, https://github.com/anotherbyte-net/leaf-focus/issues
Classifier: Development Status :: 4 - Beta
Classifier: License :: OSI Approved :: Apache Software License
Classifier: Operating System :: POSIX :: Linux
Classifier: Operating System :: Microsoft :: Windows
Classifier: Environment :: Console
Classifier: Programming Language :: Python
Classifier: Programming Language :: Python :: 3
Classifier: Programming Language :: Python :: 3 :: Only
Classifier: Programming Language :: Python :: 3.8
Classifier: Programming Language :: Python :: 3.9
Classifier: Programming Language :: Python :: 3.10
Classifier: Programming Language :: Python :: 3.11
Classifier: Topic :: Software Development :: Libraries :: Python Modules
Classifier: Topic :: Scientific/Engineering :: Information Analysis
Classifier: Topic :: Utilities
Requires-Python: >=3.8
License-File: LICENSE
Requires-Dist: keras-ocr (>=0.8.9)
Requires-Dist: tensorflow (>=2.9.0)
Requires-Dist: numpy (>=1.23.0)
Requires-Dist: matplotlib (>=3.6.0)
Requires-Dist: defusedxml (>=0.7.1)
Requires-Dist: importlib-resources (>=5.8.0)
Requires-Dist: importlib-metadata (>=6.0.0)
Provides-Extra: dev
Requires-Dist: pip ; extra == 'dev'
Requires-Dist: setuptools ; extra == 'dev'
Requires-Dist: wheel ; extra == 'dev'
Requires-Dist: build ; extra == 'dev'
Requires-Dist: twine ; extra == 'dev'
Requires-Dist: pip-audit ; extra == 'dev'
Requires-Dist: pytest ; extra == 'dev'
Requires-Dist: pytest-mock ; extra == 'dev'
Requires-Dist: pytest-cov ; extra == 'dev'
Requires-Dist: tblib ; extra == 'dev'
Requires-Dist: tox ; extra == 'dev'
Requires-Dist: coverage ; extra == 'dev'
Requires-Dist: hypothesis ; extra == 'dev'
Requires-Dist: black ; extra == 'dev'
Requires-Dist: ruff ; extra == 'dev'
Requires-Dist: mypy ; extra == 'dev'
Requires-Dist: pylint ; extra == 'dev'
Requires-Dist: types-dateparser ; extra == 'dev'
Requires-Dist: types-PyYAML ; extra == 'dev'
Requires-Dist: types-requests ; extra == 'dev'
Requires-Dist: types-backports ; extra == 'dev'
Requires-Dist: types-urllib3 ; extra == 'dev'
Requires-Dist: pdoc ; extra == 'dev'
